navJson/jsonParsing.py
navigate_json-1.0.8.dist-info/LICENSE
navigate_json-1.0.8.dist-info/METADATA
navigate_json-1.0.8.dist-info/WHEEL
navigate_json-1.0.8.dist-info/top_level.txt
navigate_json-1.0.8.dist-info/RECORD
