Metadata-Version: 2.1
Name: navigate-json
Version: 1.0.8
Summary: A Python package to inpsect/manage json objects.
Home-page: https://https://github.com/70Shubham07/json_navigator
Author: 70Shubham07
Author-email: shubhamkwwr5@gmail.com
License: MIT
Platform: UNKNOWN
Classifier: License :: OSI Approved :: MIT License
Classifier: Programming Language :: Python :: 3
Classifier: Programming Language :: Python :: 3.7
